mab/__init__.py
mab/algs.py
mab/tests/__init__.py
mab/tests/test_algs.py
mabalgs-0.4.3.dist-info/LICENSE
mabalgs-0.4.3.dist-info/METADATA
mabalgs-0.4.3.dist-info/WHEEL
mabalgs-0.4.3.dist-info/top_level.txt
mabalgs-0.4.3.dist-info/RECORD
