Metadata-Version: 2.1
Name: mabalgs
Version: 0.4.3
Summary: Multi-armed bandit algorithms
Home-page: https://github.com/alison-carrera/mabalgs
Author: Alison Carrera
Author-email: alison.carrera2007@gmail.com
License: Apache 2.0
Platform: UNKNOWN
Requires-Dist: numpy
